Workbook

Sheet Market_Data_Raw
A1: NIFTY 50 SENTIMENT ENGINE — RAW MARKET DATA
A2: Date | B2: Nifty_Close | C2: India_VIX | D2: FII_Net (Cr) | E2: DII_Net (Cr) | F2: PCR | G2: News_Headline | H2: BERT_Sentiment
A3: 45658 | B3: 24000 | C3: 19 | D3: -404 | E3: -322 | F3: 0.9837 | G3: India corporate bond market sees ₹9,200 Cr issuances this week | H3: 0
A4: 45659 | B4: 23979 | C4: 17.41 | D4: 473 | E4: -474 | F4: 1.0591 | G4: India renewable energy capacity crosses 250 GW milestone | H4: 1
A5: 45660 | B5: 24118.61 | C5: 18.56 | D5: 1692 | E5: -1237 | F5: 1.0194 | G5: India container throughput at ports up 12% YoY: ministry data | H5: 1
A6: 45661 | B6: 24440.2 | C6: 21.06 | D6: 408 | E6: -472 | F6: 0.9531 | G6: Wipro beats estimates, stock rallies 6.1% in morning trade | H6: 1
A7: 45662 | B7: 24398.92 | C7: 22.05 | D7: 179 | E7: 646 | F7: 0.8831 | G7: India PMI manufacturing at 53.8, in-line with consensus forecast | H7: 0
A8: 45663 | B8: 24357.72 | C8: 19.9 | D8: -549 | E8: -28 | F8: 1.0123 | G8: Nifty Realty consolidates near 52-week high; sector factors priced in | H8: 0
A9: 45664 | B9: 24694.29 | C9: 19.17 | D9: 999 | E9: 1067 | F9: 0.9648 | G9: US tariff threat on Indian pharma exports, sector falls 3.1% | H9: -1
A10: 45665 | B10: 24863.36 | C10: 20.6 | D10: 287 | E10: 318 | F10: 1.0464 | G10: Sebi board meeting to address F&O regulations; market on hold | H10: 0
A11: 45666 | B11: 24771.77 | C11: 19.54 | D11: -866 | E11: 682 | F11: 0.9993 | G11: Nifty Pharma down 2.1% as US FDA sends warning letter to firm | H11: -1
A12: 45667 | B12: 24893.74 | C12: 19.95 | D12: 491 | E12: -450 | F12: 1.0552 | G12: IT major mid-quarter update shows steady but unspectacular growth | H12: 0
A13: 45668 | B13: 24803.32 | C13: 20.72 | D13: -841 | E13: 929 | F13: 0.8766 | G13: Hero MotoCorp sales beat estimates; two-wheeler stocks rally | H13: 1
A14: 45669 | B14: 24712.74 | C14: 19.39 | D14: -182 | E14: -6 | F14: 1.0789 | G14: Bajaj Finance Q4 AUM growth at 28%, NBFC sector leads gains | H14: 1
... A252: 45907 | B252: 25620.25 | C252: 17.69 | D252: -15 | E252: -79 | F252: 0.9234 | G252: Nifty Bank trades in 200-point range ahead of RBI credit policy | H252: 0

Sheet Quantitative_Model
A1: QUANTITATIVE MODEL — LOG RETURNS, VOLATILITY & SIGNALS
A2: Date | B2: Nifty_Close | C2: Log_Returns | D2: Volatility_Regime | E2: Inst_Flow (Cr) | F2: PCR_Signal | G2: Next_Day_Trend
A3: =Market_Data_Raw!A3 -> 45658 | B3: =Market_Data_Raw!B3 -> 24000 | C3: N/A | D3: =IF(Market_Data_Raw!C3>20,"High Risk","Stable") -> Stable | E3: =Market_Data_Raw!D3+Market_Data_Raw!E3 -> -726 | F3: =IF(Market_Data_Raw!F3<0.8,-1,IF(Market_Data_Raw!F3>1,1,0)) -> 0 | G3: =IF(Market_Data_Raw!B4>Market_Data_Raw!B3,1,-1) -> -1
A4: =Market_Data_Raw!A4 -> 45659 | B4: =Market_Data_Raw!B4 -> 23979 | C4: =LN(Market_Data_Raw!B4/Market_Data_Raw!B3) -> -0.00087538304 | D4: =IF(Market_Data_Raw!C4>20,"High Risk","Stable") -> Stable | E4: =Market_Data_Raw!D4+Market_Data_Raw!E4 -> -1 | F4: =IF(Market_Data_Raw!F4<0.8,-1,IF(Market_Data_Raw!F4>1,1,0)) -> 1 | G4: =IF(Market_Data_Raw!B5>Market_Data_Raw!B4,1,-1) -> 1
A5: =Market_Data_Raw!A5 -> 45660 | B5: =Market_Data_Raw!B5 -> 24118.61 | C5: =LN(Market_Data_Raw!B5/Market_Data_Raw!B4) -> 0.0058052944 | D5: =IF(Market_Data_Raw!C5>20,"High Risk","Stable") -> Stable | E5: =Market_Data_Raw!D5+Market_Data_Raw!E5 -> 455 | F5: =IF(Market_Data_Raw!F5<0.8,-1,IF(Market_Data_Raw!F5>1,1,0)) -> 1 | G5: =IF(Market_Data_Raw!B6>Market_Data_Raw!B5,1,-1) -> 1
A6: =Market_Data_Raw!A6 -> 45661 | B6: =Market_Data_Raw!B6 -> 24440.2 | C6: =LN(Market_Data_Raw!B6/Market_Data_Raw!B5) -> 0.013245576 | D6: =IF(Market_Data_Raw!C6>20,"High Risk","Stable") -> High Risk | E6: =Market_Data_Raw!D6+Market_Data_Raw!E6 -> -64 | F6: =IF(Market_Data_Raw!F6<0.8,-1,IF(Market_Data_Raw!F6>1,1,0)) -> 0 | G6: =IF(Market_Data_Raw!B7>Market_Data_Raw!B6,1,-1) -> -1
A7: =Market_Data_Raw!A7 -> 45662 | B7: =Market_Data_Raw!B7 -> 24398.92 | C7: =LN(Market_Data_Raw!B7/Market_Data_Raw!B6) -> -0.0016904486 | D7: =IF(Market_Data_Raw!C7>20,"High Risk","Stable") -> High Risk | E7: =Market_Data_Raw!D7+Market_Data_Raw!E7 -> 825 | F7: =IF(Market_Data_Raw!F7<0.8,-1,IF(Market_Data_Raw!F7>1,1,0)) -> 0 | G7: =IF(Market_Data_Raw!B8>Market_Data_Raw!B7,1,-1) -> -1
A8: =Market_Data_Raw!A8 -> 45663 | B8: =Market_Data_Raw!B8 -> 24357.72 | C8: =LN(Market_Data_Raw!B8/Market_Data_Raw!B7) -> -0.0016900266 | D8: =IF(Market_Data_Raw!C8>20,"High Risk","Stable") -> Stable | E8: =Market_Data_Raw!D8+Market_Data_Raw!E8 -> -577 | F8: =IF(Market_Data_Raw!F8<0.8,-1,IF(Market_Data_Raw!F8>1,1,0)) -> 1 | G8: =IF(Market_Data_Raw!B9>Market_Data_Raw!B8,1,-1) -> 1
A9: =Market_Data_Raw!A9 -> 45664 | B9: =Market_Data_Raw!B9 -> 24694.29 | C9: =LN(Market_Data_Raw!B9/Market_Data_Raw!B8) -> 0.0137232 | D9: =IF(Market_Data_Raw!C9>20,"High Risk","Stable") -> Stable | E9: =Market_Data_Raw!D9+Market_Data_Raw!E9 -> 2066 | F9: =IF(Market_Data_Raw!F9<0.8,-1,IF(Market_Data_Raw!F9>1,1,0)) -> 0 | G9: =IF(Market_Data_Raw!B10>Market_Data_Raw!B9,1,-1) -> 1
A10: =Market_Data_Raw!A10 -> 45665 | B10: =Market_Data_Raw!B10 -> 24863.36 | C10: =LN(Market_Data_Raw!B10/Market_Data_Raw!B9) -> 0.006823191 | D10: =IF(Market_Data_Raw!C10>20,"High Risk","Stable") -> High Risk | E10: =Market_Data_Raw!D10+Market_Data_Raw!E10 -> 605 | F10: =IF(Market_Data_Raw!F10<0.8,-1,IF(Market_Data_Raw!F10>1,1,0)) -> 1 | G10: =IF(Market_Data_Raw!B11>Market_Data_Raw!B10,1,-1) -> -1
A11: =Market_Data_Raw!A11 -> 45666 | B11: =Market_Data_Raw!B11 -> 24771.77 | C11: =LN(Market_Data_Raw!B11/Market_Data_Raw!B10) -> -0.0036905355 | D11: =IF(Market_Data_Raw!C11>20,"High Risk","Stable") -> Stable | E11: =Market_Data_Raw!D11+Market_Data_Raw!E11 -> -184 | F11: =IF(Market_Data_Raw!F11<0.8,-1,IF(Market_Data_Raw!F11>1,1,0)) -> 0 | G11: =IF(Market_Data_Raw!B12>Market_Data_Raw!B11,1,-1) -> 1
A12: =Market_Data_Raw!A12 -> 45667 | B12: =Market_Data_Raw!B12 -> 24893.74 | C12: =LN(Market_Data_Raw!B12/Market_Data_Raw!B11) -> 0.0049116679 | D12: =IF(Market_Data_Raw!C12>20,"High Risk","Stable") -> Stable | E12: =Market_Data_Raw!D12+Market_Data_Raw!E12 -> 41 | F12: =IF(Market_Data_Raw!F12<0.8,-1,IF(Market_Data_Raw!F12>1,1,0)) -> 1 | G12: =IF(Market_Data_Raw!B13>Market_Data_Raw!B12,1,-1) -> -1
A13: =Market_Data_Raw!A13 -> 45668 | B13: =Market_Data_Raw!B13 -> 24803.32 | C13: =LN(Market_Data_Raw!B13/Market_Data_Raw!B12) -> -0.0036388511 | D13: =IF(Market_Data_Raw!C13>20,"High Risk","Stable") -> High Risk | E13: =Market_Data_Raw!D13+Market_Data_Raw!E13 -> 88 | F13: =IF(Market_Data_Raw!F13<0.8,-1,IF(Market_Data_Raw!F13>1,1,0)) -> 0 | G13: =IF(Market_Data_Raw!B14>Market_Data_Raw!B13,1,-1) -> -1
A14: =Market_Data_Raw!A14 -> 45669 | B14: =Market_Data_Raw!B14 -> 24712.74 | C14: =LN(Market_Data_Raw!B14/Market_Data_Raw!B13) -> -0.003658615 | D14: =IF(Market_Data_Raw!C14>20,"High Risk","Stable") -> Stable | E14: =Market_Data_Raw!D14+Market_Data_Raw!E14 -> -188 | F14: =IF(Market_Data_Raw!F14<0.8,-1,IF(Market_Data_Raw!F14>1,1,0)) -> 1 | G14: =IF(Market_Data_Raw!B15>Market_Data_Raw!B14,1,-1) -> 1
A15: =Market_Data_Raw!A15 -> 45670 | B15: =Market_Data_Raw!B15 -> 24771.05 | C15: =LN(Market_Data_Raw!B15/Market_Data_Raw!B14) -> 0.0023567325 | D15: =IF(Market_Data_Raw!C15>20,"High Risk","Stable") -> Stable | E15: =Market_Data_Raw!D15+Market_Data_Raw!E15 -> 367 | F15: =IF(Market_Data_Raw!F15<0.8,-1,IF(Market_Data_Raw!F15>1,1,0)) -> 0 | G15: =IF(Market_Data_Raw!B16>Market_Data_Raw!B15,1,-1) -> -1
... A251: =Market_Data_Raw!A251 -> 45906 | B251: =Market_Data_Raw!B251 -> 25524.55 | C251: =LN(Market_Data_Raw!B251/Market_Data_Raw!B250) -> 0.015306235 | D251: =IF(Market_Data_Raw!C251>20,"High Risk","Stable") -> Stable | E251: =Market_Data_Raw!D251+Market_Data_Raw!E251 -> 1063 | F251: =IF(Market_Data_Raw!F251<0.8,-1,IF(Market_Data_Raw!F251>1,1,0)) -> 0 | G251: =IF(Market_Data_Raw!B252>Market_Data_Raw!B251,1,-1) -> 1
A252: =Market_Data_Raw!A252 -> 45907 | B252: =Market_Data_Raw!B252 -> 25620.25 | C252: =LN(Market_Data_Raw!B252/Market_Data_Raw!B251) -> 0.0037423203 | D252: =IF(Market_Data_Raw!C252>20,"High Risk","Stable") -> Stable | E252: =Market_Data_Raw!D252+Market_Data_Raw!E252 -> -94 | F252: =IF(Market_Data_Raw!F252<0.8,-1,IF(Market_Data_Raw!F252>1,1,0)) -> 0 | G252: -1

Sheet Qualitative_Sentiment
A1: QUALITATIVE SENTIMENT — NLP & BERT ANALYSIS
A2: Date | B2: News_Headline | C2: BERT_Sentiment | D2: Sentiment_Category | E2: Market_Impact | F2: Signal_Accuracy
A3: =Market_Data_Raw!A3 -> 45658 | B3: =Market_Data_Raw!G3 -> India corporate bond market sees ₹9,200 Cr issuances this week | C3: =Market_Data_Raw!H3 -> 0 | D3: =IF(C3=1,"Positive",IF(C3=-1,"Negative","Neutral")) -> Neutral | E3: =IF(Quantitative_Model!G3=1,"Upward","Downward") -> Downward | F3: =IF(C3=Quantitative_Model!G3,"Correct","Incorrect") -> Incorrect
A4: =Market_Data_Raw!A4 -> 45659 | B4: =Market_Data_Raw!G4 -> India renewable energy capacity crosses 250 GW milestone | C4: =Market_Data_Raw!H4 -> 1 | D4: =IF(C4=1,"Positive",IF(C4=-1,"Negative","Neutral")) -> Positive | E4: =IF(Quantitative_Model!G4=1,"Upward","Downward") -> Upward | F4: =IF(C4=Quantitative_Model!G4,"Correct","Incorrect") -> Correct
A5: =Market_Data_Raw!A5 -> 45660 | B5: =Market_Data_Raw!G5 -> India container throughput at ports up 12% YoY: ministry data | C5: =Market_Data_Raw!H5 -> 1 | D5: =IF(C5=1,"Positive",IF(C5=-1,"Negative","Neutral")) -> Positive | E5: =IF(Quantitative_Model!G5=1,"Upward","Downward") -> Upward | F5: =IF(C5=Quantitative_Model!G5,"Correct","Incorrect") -> Correct
A6: =Market_Data_Raw!A6 -> 45661 | B6: =Market_Data_Raw!G6 -> Wipro beats estimates, stock rallies 6.1% in morning trade | C6: =Market_Data_Raw!H6 -> 1 | D6: =IF(C6=1,"Positive",IF(C6=-1,"Negative","Neutral")) -> Positive | E6: =IF(Quantitative_Model!G6=1,"Upward","Downward") -> Downward | F6: =IF(C6=Quantitative_Model!G6,"Correct","Incorrect") -> Incorrect
A7: =Market_Data_Raw!A7 -> 45662 | B7: =Market_Data_Raw!G7 -> India PMI manufacturing at 53.8, in-line with consensus forecast | C7: =Market_Data_Raw!H7 -> 0 | D7: =IF(C7=1,"Positive",IF(C7=-1,"Negative","Neutral")) -> Neutral | E7: =IF(Quantitative_Model!G7=1,"Upward","Downward") -> Downward | F7: =IF(C7=Quantitative_Model!G7,"Correct","Incorrect") -> Incorrect
A8: =Market_Data_Raw!A8 -> 45663 | B8: =Market_Data_Raw!G8 -> Nifty Realty consolidates near 52-week high; sector factors priced in | C8: =Market_Data_Raw!H8 -> 0 | D8: =IF(C8=1,"Positive",IF(C8=-1,"Negative","Neutral")) -> Neutral | E8: =IF(Quantitative_Model!G8=1,"Upward","Downward") -> Upward | F8: =IF(C8=Quantitative_Model!G8,"Correct","Incorrect") -> Incorrect
A9: =Market_Data_Raw!A9 -> 45664 | B9: =Market_Data_Raw!G9 -> US tariff threat on Indian pharma exports, sector falls 3.1% | C9: =Market_Data_Raw!H9 -> -1 | D9: =IF(C9=1,"Positive",IF(C9=-1,"Negative","Neutral")) -> Negative | E9: =IF(Quantitative_Model!G9=1,"Upward","Downward") -> Upward | F9: =IF(C9=Quantitative_Model!G9,"Correct","Incorrect") -> Incorrect
A10: =Market_Data_Raw!A10 -> 45665 | B10: =Market_Data_Raw!G10 -> Sebi board meeting to address F&O regulations; market on hold | C10: =Market_Data_Raw!H10 -> 0 | D10: =IF(C10=1,"Positive",IF(C10=-1,"Negative","Neutral")) -> Neutral | E10: =IF(Quantitative_Model!G10=1,"Upward","Downward") -> Downward | F10: =IF(C10=Quantitative_Model!G10,"Correct","Incorrect") -> Incorrect
A11: =Market_Data_Raw!A11 -> 45666 | B11: =Market_Data_Raw!G11 -> Nifty Pharma down 2.1% as US FDA sends warning letter to firm | C11: =Market_Data_Raw!H11 -> -1 | D11: =IF(C11=1,"Positive",IF(C11=-1,"Negative","Neutral")) -> Negative | E11: =IF(Quantitative_Model!G11=1,"Upward","Downward") -> Upward | F11: =IF(C11=Quantitative_Model!G11,"Correct","Incorrect") -> Incorrect
A12: =Market_Data_Raw!A12 -> 45667 | B12: =Market_Data_Raw!G12 -> IT major mid-quarter update shows steady but unspectacular growth | C12: =Market_Data_Raw!H12 -> 0 | D12: =IF(C12=1,"Positive",IF(C12=-1,"Negative","Neutral")) -> Neutral | E12: =IF(Quantitative_Model!G12=1,"Upward","Downward") -> Downward | F12: =IF(C12=Quantitative_Model!G12,"Correct","Incorrect") -> Incorrect
A13: =Market_Data_Raw!A13 -> 45668 | B13: =Market_Data_Raw!G13 -> Hero MotoCorp sales beat estimates; two-wheeler stocks rally | C13: =Market_Data_Raw!H13 -> 1 | D13: =IF(C13=1,"Positive",IF(C13=-1,"Negative","Neutral")) -> Positive | E13: =IF(Quantitative_Model!G13=1,"Upward","Downward") -> Downward | F13: =IF(C13=Quantitative_Model!G13,"Correct","Incorrect") -> Incorrect
A14: =Market_Data_Raw!A14 -> 45669 | B14: =Market_Data_Raw!G14 -> Bajaj Finance Q4 AUM growth at 28%, NBFC sector leads gains | C14: =Market_Data_Raw!H14 -> 1 | D14: =IF(C14=1,"Positive",IF(C14=-1,"Negative","Neutral")) -> Positive | E14: =IF(Quantitative_Model!G14=1,"Upward","Downward") -> Upward | F14: =IF(C14=Quantitative_Model!G14,"Correct","Incorrect") -> Correct
... A252: =Market_Data_Raw!A252 -> 45907 | B252: =Market_Data_Raw!G252 -> Nifty Bank trades in 200-point range ahead of RBI credit policy | C252: =Market_Data_Raw!H252 -> 0 | D252: =IF(C252=1,"Positive",IF(C252=-1,"Negative","Neutral")) -> Neutral | E252: =IF(Quantitative_Model!G252=1,"Upward","Downward") -> Downward | F252: =IF(C252=Quantitative_Model!G252,"Correct","Incorrect") -> Incorrect

Sheet Analytics_Tables
A1: ANALYTICS TABLES — DESCRIPTIVE STATISTICS & RISK INSIGHTS
A3: STUDY 1A — DESCRIPTIVE STATISTICS | E3: STUDY 1B — RISK ANALYSIS (Volatility Regime)
A5: Statistic | B5: Log_Returns | C5: India_VIX | E5: Regime | F5: Avg Log Return | G5: Count | H5: Avg VIX
A6: Observations | B6: 250 | C6: 250 | E6: Stable | F6: 0.00019 | G6: 181 | H6: 17.07
A7: Mean | B7: 0.000262 | C7: 18.3918 | E7: High Risk | F7: 0.000451 | G7: 69 | H7: 21.86
A8: Median | B8: 0.000795 | C8: 18.21
A9: Std Deviation | B9: 0.008224 | C9: 2.7701 | E9: TOTAL | G9: 250
A10: Minimum | B10: -0.021968 | C10: 11.85
A11: Maximum | B11: 0.033048 | C11: 25.51
A12: Skewness | B12: 0.3105 | C12: 0.1855
A13: STUDY 2 — BERT SENTIMENT ACCURACY | E13: STUDY 3 — PCR SIGNAL ACCURACY
A14: Variance | B14: 6.763e-05 | C14: 7.6734
A15: BERT Sentiment | B15: Total Count | C15: Correct | D15: Accuracy % | E15: PCR Signal | F15: Total | G15: Correct | H15: Accuracy %
A16: Positive | B16: 114 | C16: 67 | D16: 58.8 | E16: Bearish (-1) | F16: 46 | G16: 23 | H16: 50.0%
A17: Neutral | B17: 74 | C17: 0 | D17: 0 | E17: Neutral (0) | F17: 133 | G17: 0 | H17: 0.0%
A18: Negative | B18: 62 | C18: 29 | D18: 46.8 | E18: Bullish (+1) | F18: 71 | G18: 36 | H18: 50.7%

Sheet Dashboard
B2: NIFTY 50 SENTIMENT ENGINE — MANAGERIAL DASHBOARD | FY 2025
B3: Naik & Inamdar (2024) Research Framework | Data: 01-Jan-2025 to 07-Sep-2025 | Observation Period: 250 Trading Days
B5: TOTAL SAMPLES | G5: PCR WIN RATE | L5: AVG. VOLATILITY (VIX)
B6: 250 | G6: 23.6% | L6: 18.39
B7: Trading Days Observed | G7: PCR Signal Prediction Accuracy | L7: India VIX Average (Observation Period)
B9: ● KEY MARKET CHARTS
H33: PCR Signal | I33: Count
H34: Bearish | I34: 46
H35: Neutral | I35: 133
H36: Bullish | I36: 71
B55: ● SUMMARY STATISTICS | ● SLICER & TIMELINE NOTE
B56: Market Overview | C56: Nifty50 opened at ₹24,000 and closed at ₹25,620 — a +6.8% period return.
B57: Volatility Profile | C57: India VIX ranged from 11.8 to 25.5. Avg VIX = 18.39. High-Risk days: 69.
B58: PCR Signal Accuracy | C58: Bullish signals: 71 days, Neutral: 133, Bearish: 46. Win Rate: 23.6%.
B59: BERT Sentiment | C59: Positive news: 114 days, Neutral: 74, Negative: 62.
B60: Institutional Flow | C60: FII net flows ranged ₹-2,646 to ₹2,766 Cr. DII flows partially offset FII activity.
B61: Interactive Filters | C61: ⚡ Insert SLICER for Volatility_Regime & BERT_Sentiment from Analytics_Tables pivot. Insert TIMELINE for Date filtering.
